sobiraka/VERSION
sobiraka/__init__.py
sobiraka/__main__.py
sobiraka/files/sobiraka-nav.yaml
sobiraka/files/sobiraka-project.yaml
sobiraka/files/dictionaries/README.md
sobiraka/files/dictionaries/english.aff
sobiraka/files/dictionaries/english.dic
sobiraka/files/dictionaries/russian.aff
sobiraka/files/dictionaries/russian.dic
sobiraka/files/themes/book/extension.py
sobiraka/files/themes/book/web.html
sobiraka/files/themes/book/_static/book.min.css
sobiraka/files/themes/book/_static/favicon.png
sobiraka/files/themes/book/_static/svg/calendar.svg
sobiraka/files/themes/book/_static/svg/edit.svg
sobiraka/files/themes/book/_static/svg/menu.svg
sobiraka/files/themes/book/_static/svg/toc.svg
sobiraka/files/themes/book/_static/svg/translate.svg
sobiraka/files/themes/book/sass/_code.scss
sobiraka/files/themes/book/sass/_fonts.scss
sobiraka/files/themes/book/sass/_logo.scss
sobiraka/files/themes/book/sass/_search.scss
sobiraka/files/themes/book/sass/additional.scss
sobiraka/files/themes/material/extension.py
sobiraka/files/themes/material/web.html
sobiraka/files/themes/material/_static/check-solid.svg
sobiraka/files/themes/material/_static/clipboard.min.js
sobiraka/files/themes/material/_static/doctools.js
sobiraka/files/themes/material/_static/documentation_options.js
sobiraka/files/themes/material/_static/jquery.js
sobiraka/files/themes/material/_static/jquery.min.map
sobiraka/files/themes/material/_static/material.css
sobiraka/files/themes/material/_static/material.css_t
sobiraka/files/themes/material/_static/rtd_sphinx_search.min.css
sobiraka/files/themes/material/_static/underscore.js
sobiraka/files/themes/material/_static/fonts/font-awesome.css
sobiraka/files/themes/material/_static/fonts/material-icons.css
sobiraka/files/themes/material/_static/fonts/specimen/FontAwesome.ttf
sobiraka/files/themes/material/_static/fonts/specimen/FontAwesome.woff
sobiraka/files/themes/material/_static/fonts/specimen/FontAwesome.woff2
sobiraka-0.9.1.dist-info/METADATA
sobiraka-0.9.1.dist-info/WHEEL
sobiraka-0.9.1.dist-info/entry_points.txt
sobiraka-0.9.1.dist-info/licenses/LICENSE
sobiraka-0.9.1.dist-info/RECORD
